fabrial_core_plugins/__init__.py
fabrial_core_plugins/flow_control/__init__.py
fabrial_core_plugins/flow_control/items/__init__.py
fabrial_core_plugins/flow_control/items/hold/__init__.py
fabrial_core_plugins/flow_control/items/hold/clock-select.png
fabrial_core_plugins/flow_control/items/hold/hold_item.py
fabrial_core_plugins/flow_control/items/hold/hold_step.py
fabrial_core_plugins/flow_control/items/hold/hold_widget.py
fabrial_core_plugins/flow_control/items/loop/__init__.py
fabrial_core_plugins/flow_control/items/loop/arrow-repeat.png
fabrial_core_plugins/flow_control/items/loop/loop_item.py
fabrial_core_plugins/flow_control/items/loop/loop_step.py
fabrial_core_plugins/flow_control/items/loop/loop_widget.py
fabrial_core_plugins/flow_control/items/simultaneous/__init__.py
fabrial_core_plugins/flow_control/items/simultaneous/arrow-in.png
fabrial_core_plugins/flow_control/items/simultaneous/simultaneous_item.py
fabrial_core_plugins/flow_control/items/simultaneous/simultaneous_step.py
fabrial_core_plugins/flow_control/items/simultaneous/simultaneous_widget.py
fabrial_core_plugins-0.2.1.dist-info/METADATA
fabrial_core_plugins-0.2.1.dist-info/WHEEL
fabrial_core_plugins-0.2.1.dist-info/entry_points.txt
fabrial_core_plugins-0.2.1.dist-info/licenses/LICENSE
fabrial_core_plugins-0.2.1.dist-info/RECORD
