Metadata-Version: 2.4
Name: fabrial-core-plugins
Version: 0.2.1
Summary: Built-in plugins for Fabrial.
Project-URL: Repository, https://github.com/Maughan-Lab/fabrial-core-plugins
License-File: LICENSE
Requires-Python: >=3.13
Requires-Dist: fabrial
